hubspot_etl_pipeline_webserver/__init__.py
hubspot_etl_pipeline_webserver/bigquery_helper.py
hubspot_etl_pipeline_webserver/downloader.py
hubspot_etl_pipeline_webserver/hubspot_helper.py
hubspot_etl_pipeline_webserver/prototype.py
hubspot_etl_pipeline_webserver/webserver.py
hubspot_etl_pipeline_webserver-0.0.10.dist-info/METADATA
hubspot_etl_pipeline_webserver-0.0.10.dist-info/WHEEL
hubspot_etl_pipeline_webserver-0.0.10.dist-info/licenses/LICENSE
hubspot_etl_pipeline_webserver-0.0.10.dist-info/RECORD
